[
    {
        "id": "e1de4893-099f-417d-8d9d-1d13cfc601d6",
        "created_at": "2024-02-23T09:00:40.215294+00:00",
        "name": "Stockport County FC",
        "league_id": "0fe62252-964c-4b5d-9e72-86567613451a",
        "position": 1,
        "footystats_url": "https://footystats.org/clubs/stockport-county-fc-3143",
        "primatips_url": null,
        "flashscore_name": "Stockport County",
        "flashscore_url": "https://www.flashscore.com//team/stockport-county/IX6WjNvr/",
        "league_name": "EFL League Two",
        "league_country": "England"
    },
    {
        "id": "c9fdfc06-a29a-4260-a54b-efe496cab2eb",
        "created_at": "2024-02-23T09:00:40.215294+00:00",
        "name": "Mansfield Town FC",
        "league_id": "0fe62252-964c-4b5d-9e72-86567613451a",
        "position": 2,
        "footystats_url": "https://footystats.org/clubs/mansfield-town-fc-267",
        "primatips_url": null,
        "flashscore_name": "Mansfield",
        "flashscore_url": "https://www.flashscore.com//team/mansfield/t6G9wMZN/",
        "league_name": "EFL League Two",
        "league_country": "England"
    },
    {
        "id": "32f73786-0379-43c8-bda6-dea57d5c2744",
        "created_at": "2024-02-23T09:00:40.215294+00:00",
        "name": "Wrexham FC",
        "league_id": "0fe62252-964c-4b5d-9e72-86567613451a",
        "position": 3,
        "footystats_url": "https://footystats.org/clubs/wrexham-fc-1837",
        "primatips_url": null,
        "flashscore_name": "Wrexham",
        "flashscore_url": "https://www.flashscore.com//team/wrexham/IgO7K1ZA/",
        "league_name": "EFL League Two",
        "league_country": "England"
    },
    {
        "id": "45db25de-bea5-4bc1-8d0d-220665ca8ad3",
        "created_at": "2024-02-23T09:00:40.215294+00:00",
        "name": "Crewe Alexandra FC",
        "league_id": "0fe62252-964c-4b5d-9e72-86567613451a",
        "position": 4,
        "footystats_url": "https://footystats.org/clubs/crewe-alexandra-fc-252",
        "primatips_url": null,
        "flashscore_name": "Crewe",
        "flashscore_url": "https://www.flashscore.com//team/crewe/YacqHHdS/",
        "league_name": "EFL League Two",
        "league_country": "England"
    },
    {
        "id": "526b711c-c6ed-44f3-a294-9f5986cffc4d",
        "created_at": "2024-02-23T09:00:40.215294+00:00",
        "name": "Milton Keynes Dons FC",
        "league_id": "0fe62252-964c-4b5d-9e72-86567613451a",
        "position": 5,
        "footystats_url": "https://footystats.org/clubs/milton-keynes-dons-fc-227",
        "primatips_url": null,
        "flashscore_name": "MK Dons",
        "flashscore_url": "https://www.flashscore.com//team/milton-keynes-dons/f9KDxtkU/",
        "league_name": "EFL League Two",
        "league_country": "England"
    },
    {
        "id": "2ab26b59-787e-4349-9011-d9468ac976ba",
        "created_at": "2024-02-23T09:00:40.215294+00:00",
        "name": "Barrow AFC",
        "league_id": "0fe62252-964c-4b5d-9e72-86567613451a",
        "position": 6,
        "footystats_url": "https://footystats.org/clubs/barrow-afc-1833",
        "primatips_url": null,
        "flashscore_name": "Barrow",
        "flashscore_url": "https://www.flashscore.com//team/barrow/KKJL7QXd/",
        "league_name": "EFL League Two",
        "league_country": "England"
    },
    {
        "id": "86a0e659-1fea-4bee-ac54-48df04b0d1bf",
        "created_at": "2024-02-23T09:00:40.215294+00:00",
        "name": "Harrogate Town FC",
        "league_id": "0fe62252-964c-4b5d-9e72-86567613451a",
        "position": 7,
        "footystats_url": "https://footystats.org/clubs/harrogate-town-fc-3124",
        "primatips_url": null,
        "flashscore_name": "Harrogate",
        "flashscore_url": "https://www.flashscore.com//team/harrogate/CQv5qrFt/",
        "league_name": "EFL League Two",
        "league_country": "England"
    },
    {
        "id": "911de780-14ac-4e77-ae5e-4d5a38d8dfce",
        "created_at": "2024-02-23T09:00:40.215294+00:00",
        "name": "Gillingham FC",
        "league_id": "0fe62252-964c-4b5d-9e72-86567613451a",
        "position": 8,
        "footystats_url": "https://footystats.org/clubs/gillingham-fc-238",
        "primatips_url": null,
        "flashscore_name": "Gillingham",
        "flashscore_url": "https://www.flashscore.com//team/gillingham/WvZyDeKk/",
        "league_name": "EFL League Two",
        "league_country": "England"
    },
    {
        "id": "924630be-f546-47c9-82c8-02bf736787fb",
        "created_at": "2024-02-23T09:00:40.215294+00:00",
        "name": "AFC Wimbledon",
        "league_id": "0fe62252-964c-4b5d-9e72-86567613451a",
        "position": 9,
        "footystats_url": "https://footystats.org/clubs/afc-wimbledon-241",
        "primatips_url": null,
        "flashscore_name": "AFC Wimbledon",
        "flashscore_url": "https://www.flashscore.com//team/afc-wimbledon/4KREuF43/",
        "league_name": "EFL League Two",
        "league_country": "England"
    },
    {
        "id": "133ad48c-9335-4d66-9c7c-3754b0ab0840",
        "created_at": "2024-02-23T09:00:40.215294+00:00",
        "name": "Notts County FC",
        "league_id": "0fe62252-964c-4b5d-9e72-86567613451a",
        "position": 10,
        "footystats_url": "https://footystats.org/clubs/notts-county-fc-256",
        "primatips_url": null,
        "flashscore_name": "Notts Co",
        "flashscore_url": "https://www.flashscore.com//team/notts-county/EwJVdqzn/",
        "league_name": "EFL League Two",
        "league_country": "England"
    },
    {
        "id": "15702e06-495c-4290-981c-11094c6a6783",
        "created_at": "2024-02-23T09:00:40.215294+00:00",
        "name": "Morecambe FC",
        "league_id": "0fe62252-964c-4b5d-9e72-86567613451a",
        "position": 11,
        "footystats_url": "https://footystats.org/clubs/morecambe-fc-270",
        "primatips_url": null,
        "flashscore_name": "Morecambe",
        "flashscore_url": "https://www.flashscore.com//team/morecambe/zmKRcPKu/",
        "league_name": "EFL League Two",
        "league_country": "England"
    },
    {
        "id": "8222ce82-4414-4369-abae-3a46d618cece",
        "created_at": "2024-02-23T09:00:40.215294+00:00",
        "name": "Accrington Stanley FC",
        "league_id": "0fe62252-964c-4b5d-9e72-86567613451a",
        "position": 12,
        "footystats_url": "https://footystats.org/clubs/accrington-stanley-fc-263",
        "primatips_url": null,
        "flashscore_name": "Accrington",
        "flashscore_url": "https://www.flashscore.com//team/accrington/6ZvdGuYf/",
        "league_name": "EFL League Two",
        "league_country": "England"
    },
    {
        "id": "96c364dd-2d03-4080-b732-d7b2130d6d57",
        "created_at": "2024-02-23T09:00:40.215294+00:00",
        "name": "Bradford City AFC",
        "league_id": "0fe62252-964c-4b5d-9e72-86567613451a",
        "position": 13,
        "footystats_url": "https://footystats.org/clubs/bradford-city-afc-248",
        "primatips_url": null,
        "flashscore_name": "Bradford City",
        "flashscore_url": "https://www.flashscore.com//team/bradford-city/bsc3EJ27/",
        "league_name": "EFL League Two",
        "league_country": "England"
    },
    {
        "id": "8d7c10f6-ef1d-4d13-871b-7f76c879d8d3",
        "created_at": "2024-02-23T09:00:40.215294+00:00",
        "name": "Crawley Town FC",
        "league_id": "0fe62252-964c-4b5d-9e72-86567613451a",
        "position": 14,
        "footystats_url": "https://footystats.org/clubs/crawley-town-fc-254",
        "primatips_url": null,
        "flashscore_name": "Crawley",
        "flashscore_url": "https://www.flashscore.com//team/crawley-town/QVmLl54o/",
        "league_name": "EFL League Two",
        "league_country": "England"
    },
    {
        "id": "adaf6b28-1fa7-4be6-8673-7d188bb9de7d",
        "created_at": "2024-02-23T09:00:40.215294+00:00",
        "name": "Newport County AFC",
        "league_id": "0fe62252-964c-4b5d-9e72-86567613451a",
        "position": 15,
        "footystats_url": "https://footystats.org/clubs/newport-county-afc-265",
        "primatips_url": null,
        "flashscore_name": "Newport",
        "flashscore_url": "https://www.flashscore.com/team/newport/ChwgcrNJ/",
        "league_name": "EFL League Two",
        "league_country": "England"
    },
    {
        "id": "854c9e26-29cf-485f-9758-4e2e28288718",
        "created_at": "2024-02-23T09:00:40.215294+00:00",
        "name": "Walsall FC",
        "league_id": "0fe62252-964c-4b5d-9e72-86567613451a",
        "position": 16,
        "footystats_url": "https://footystats.org/clubs/walsall-fc-236",
        "primatips_url": null,
        "flashscore_name": "Walsall",
        "flashscore_url": "https://www.flashscore.com//team/walsall/YgrfcLuL/",
        "league_name": "EFL League Two",
        "league_country": "England"
    },
    {
        "id": "708c08de-84e1-4b37-8c33-c8f9acedd795",
        "created_at": "2024-02-23T09:00:40.215294+00:00",
        "name": "Tranmere Rovers FC",
        "league_id": "0fe62252-964c-4b5d-9e72-86567613451a",
        "position": 17,
        "footystats_url": "https://footystats.org/clubs/tranmere-rovers-fc-259",
        "primatips_url": null,
        "flashscore_name": "Tranmere",
        "flashscore_url": "https://www.flashscore.com//team/tranmere/jVhkb1QE/",
        "league_name": "EFL League Two",
        "league_country": "England"
    },
    {
        "id": "0d13ffd9-f8b9-40bb-89bc-b6b5f7b2167e",
        "created_at": "2024-02-23T09:00:40.215294+00:00",
        "name": "Swindon Town FC",
        "league_id": "0fe62252-964c-4b5d-9e72-86567613451a",
        "position": 18,
        "footystats_url": "https://footystats.org/clubs/swindon-town-fc-234",
        "primatips_url": null,
        "flashscore_name": "Swindon",
        "flashscore_url": "https://www.flashscore.com//team/swindon/xSloasB8/",
        "league_name": "EFL League Two",
        "league_country": "England"
    },
    {
        "id": "296b7733-96a8-452f-8766-8aa7122f1de1",
        "created_at": "2024-02-23T09:00:40.215294+00:00",
        "name": "Salford City FC",
        "league_id": "0fe62252-964c-4b5d-9e72-86567613451a",
        "position": 19,
        "footystats_url": "https://footystats.org/clubs/salford-city-fc-3141",
        "primatips_url": null,
        "flashscore_name": "Salford",
        "flashscore_url": "https://www.flashscore.com/team/salford/W4AadhN3/",
        "league_name": "EFL League Two",
        "league_country": "England"
    },
    {
        "id": "655a1ae3-f9ca-4ce7-b3ab-12448fdbe03b",
        "created_at": "2024-02-23T09:00:40.215294+00:00",
        "name": "Doncaster Rovers FC",
        "league_id": "0fe62252-964c-4b5d-9e72-86567613451a",
        "position": 20,
        "footystats_url": "https://footystats.org/clubs/doncaster-rovers-fc-231",
        "primatips_url": null,
        "flashscore_name": "Doncaster",
        "flashscore_url": "https://www.flashscore.com//team/doncaster/hlzYDy5q/",
        "league_name": "EFL League Two",
        "league_country": "England"
    },
    {
        "id": "f090752a-f7f6-4c8c-b176-40c4bc874d4c",
        "created_at": "2024-02-23T09:00:40.215294+00:00",
        "name": "Colchester United FC",
        "league_id": "0fe62252-964c-4b5d-9e72-86567613451a",
        "position": 21,
        "footystats_url": "https://footystats.org/clubs/colchester-united-fc-253",
        "primatips_url": null,
        "flashscore_name": "Colchester",
        "flashscore_url": "https://www.flashscore.com//team/colchester/xYu73rNn/",
        "league_name": "EFL League Two",
        "league_country": "England"
    },
    {
        "id": "b77d864e-7e5e-4aa2-9f83-d96b3afe48c6",
        "created_at": "2024-02-23T09:00:40.215294+00:00",
        "name": "Grimsby Town FC",
        "league_id": "0fe62252-964c-4b5d-9e72-86567613451a",
        "position": 22,
        "footystats_url": "https://footystats.org/clubs/grimsby-town-fc-273",
        "primatips_url": null,
        "flashscore_name": "Grimsby",
        "flashscore_url": "https://www.flashscore.com//team/grimsby/OEaiS3za/",
        "league_name": "EFL League Two",
        "league_country": "England"
    },
    {
        "id": "f1e97b24-e022-4568-8d3d-2e3510b54bf8",
        "created_at": "2024-02-23T09:00:40.215294+00:00",
        "name": "Forest Green Rovers FC",
        "league_id": "0fe62252-964c-4b5d-9e72-86567613451a",
        "position": 23,
        "footystats_url": "https://footystats.org/clubs/forest-green-rovers-fc-1020",
        "primatips_url": null,
        "flashscore_name": "Forest Green",
        "flashscore_url": "https://www.flashscore.com//team/forest-green/v7ZNnsJG/",
        "league_name": "EFL League Two",
        "league_country": "England"
    },
    {
        "id": "7d6be22e-4c06-4d7b-b5aa-76b4cbae0c63",
        "created_at": "2024-02-23T09:00:40.215294+00:00",
        "name": "Sutton United FC",
        "league_id": "0fe62252-964c-4b5d-9e72-86567613451a",
        "position": 24,
        "footystats_url": "https://footystats.org/clubs/sutton-united-fc-1827",
        "primatips_url": null,
        "flashscore_name": "Sutton",
        "flashscore_url": "https://www.flashscore.com//team/sutton/8OOOiMps/",
        "league_name": "EFL League Two",
        "league_country": "England"
    }
]