[
    {
        "id": "42030e92-f1c0-46bc-83f0-ec14ffbc11a2",
        "created_at": "2024-02-23T09:00:34.45046+00:00",
        "name": "Willem II",
        "league_id": "5498e950-c9e9-43da-9b41-f215dbc9d2ef",
        "position": 1,
        "footystats_url": "https://footystats.org/clubs/willem-ii-381",
        "primatips_url": "https:primatips.com/teams/netherlands/willem-ii-tilburg",
        "primatips_name": "Willem II",
        "league_name": "Eerste Divisie",
        "league_country": "Netherlands"
    },
    {
        "id": "adfe5751-0039-44f9-b443-37447fbae476",
        "created_at": "2024-02-23T09:00:34.45046+00:00",
        "name": "SV Roda JC",
        "league_id": "5498e950-c9e9-43da-9b41-f215dbc9d2ef",
        "position": 2,
        "footystats_url": "https://footystats.org/clubs/sv-roda-jc-368",
        "primatips_url": "https:primatips.com/teams/netherlands/roda-jc-kerkrade",
        "primatips_name": "Roda Kerkrade",
        "league_name": "Eerste Divisie",
        "league_country": "Netherlands"
    },
    {
        "id": "da5e7625-0efb-456c-b5fb-5c4f68697852",
        "created_at": "2024-02-23T09:00:34.45046+00:00",
        "name": "HFC ADO Den Haag",
        "league_id": "5498e950-c9e9-43da-9b41-f215dbc9d2ef",
        "position": 3,
        "footystats_url": "https://footystats.org/clubs/hfc-ado-den-haag-377",
        "primatips_url": "https:primatips.com/teams/netherlands/ado-den-haag",
        "primatips_name": "ADO Den Haag",
        "league_name": "Eerste Divisie",
        "league_country": "Netherlands"
    },
    {
        "id": "59e96926-eeea-420b-a76e-82ab99d617ec",
        "created_at": "2024-02-23T09:00:34.45046+00:00",
        "name": "FC Groningen",
        "league_id": "5498e950-c9e9-43da-9b41-f215dbc9d2ef",
        "position": 4,
        "footystats_url": "https://footystats.org/clubs/fc-groningen-372",
        "primatips_url": "https:primatips.com/teams/netherlands/fc-groningen",
        "primatips_name": "Groningen",
        "league_name": "Eerste Divisie",
        "league_country": "Netherlands"
    },
    {
        "id": "419885c3-bc0d-4c98-bcbb-b1070a193640",
        "created_at": "2024-02-23T09:00:34.45046+00:00",
        "name": "FC Dordrecht",
        "league_id": "5498e950-c9e9-43da-9b41-f215dbc9d2ef",
        "position": 5,
        "footystats_url": "https://footystats.org/clubs/fc-dordrecht-384",
        "primatips_url": "https:primatips.com/teams/netherlands/fc-dordrecht",
        "primatips_name": "Dordrecht",
        "league_name": "Eerste Divisie",
        "league_country": "Netherlands"
    },
    {
        "id": "3866b7b2-f4f2-45b2-9dd2-8cbc1ec56a47",
        "created_at": "2024-02-23T09:00:34.45046+00:00",
        "name": "BV De Graafschap",
        "league_id": "5498e950-c9e9-43da-9b41-f215dbc9d2ef",
        "position": 6,
        "footystats_url": "https://footystats.org/clubs/bv-de-graafschap-383",
        "primatips_url": "https:primatips.com/teams/netherlands/de-graafschap",
        "primatips_name": "De Graafschap",
        "league_name": "Eerste Divisie",
        "league_country": "Netherlands"
    },
    {
        "id": "b0993f3f-a95c-43b6-b792-72746852a53f",
        "created_at": "2024-02-23T09:00:34.45046+00:00",
        "name": "SC Cambuur Leeuwarden",
        "league_id": "5498e950-c9e9-43da-9b41-f215dbc9d2ef",
        "position": 7,
        "footystats_url": "https://footystats.org/clubs/sc-cambuur-leeuwarden-382",
        "primatips_url": "https:primatips.com/teams/netherlands/sc-cambuur",
        "primatips_name": "Cambuur",
        "league_name": "Eerste Divisie",
        "league_country": "Netherlands"
    },
    {
        "id": "b708cb35-aad6-4949-b252-637c36d4d6c9",
        "created_at": "2024-02-23T09:00:34.45046+00:00",
        "name": "Alkmaar Zaanstreek II",
        "league_id": "5498e950-c9e9-43da-9b41-f215dbc9d2ef",
        "position": 8,
        "footystats_url": "https://footystats.org/clubs/alkmaar-zaanstreek-ii-1043",
        "primatips_url": "https:primatips.com/teams/netherlands/willem-ii-tilburg",
        "primatips_name": "Willem II",
        "league_name": "Eerste Divisie",
        "league_country": "Netherlands"
    },
    {
        "id": "c824c23d-31e8-41fb-ac95-5795a6bd2594",
        "created_at": "2024-02-23T09:00:34.45046+00:00",
        "name": "NAC Breda",
        "league_id": "5498e950-c9e9-43da-9b41-f215dbc9d2ef",
        "position": 9,
        "footystats_url": "https://footystats.org/clubs/nac-breda-385",
        "primatips_url": "https:primatips.com/teams/netherlands/nac-breda",
        "primatips_name": "NAC Breda",
        "league_name": "Eerste Divisie",
        "league_country": "Netherlands"
    },
    {
        "id": "89ead0fc-cc37-48e8-8bf6-6262ef274f1c",
        "created_at": "2024-02-23T09:00:34.45046+00:00",
        "name": "VVV Venlo",
        "league_id": "5498e950-c9e9-43da-9b41-f215dbc9d2ef",
        "position": 10,
        "footystats_url": "https://footystats.org/clubs/vvv-venlo-401",
        "primatips_url": "https:primatips.com/teams/netherlands/vvv-venlo",
        "primatips_name": "VVV-Venlo",
        "league_name": "Eerste Divisie",
        "league_country": "Netherlands"
    },
    {
        "id": "61688b4c-9c8b-4129-b85b-e81e6b0cde14",
        "created_at": "2024-02-23T09:00:34.45046+00:00",
        "name": "MVV",
        "league_id": "5498e950-c9e9-43da-9b41-f215dbc9d2ef",
        "position": 11,
        "footystats_url": "https://footystats.org/clubs/mvv-388",
        "primatips_url": "https:primatips.com/teams/netherlands/mvv-maastricht",
        "primatips_name": "MVV Maastricht",
        "league_name": "Eerste Divisie",
        "league_country": "Netherlands"
    },
    {
        "id": "9e7ce5d8-c959-469b-9ee1-5ddcbd9ed4eb",
        "created_at": "2024-02-23T09:00:34.45046+00:00",
        "name": "Helmond Sport",
        "league_id": "5498e950-c9e9-43da-9b41-f215dbc9d2ef",
        "position": 12,
        "footystats_url": "https://footystats.org/clubs/helmond-sport-395",
        "primatips_url": "https:primatips.com/teams/netherlands/helmond-sport",
        "primatips_name": "Helmond Sport",
        "league_name": "Eerste Divisie",
        "league_country": "Netherlands"
    },
    {
        "id": "c025e5a7-aeaf-4dfa-a574-9a369c3e168f",
        "created_at": "2024-02-23T09:00:34.45046+00:00",
        "name": "FC Emmen",
        "league_id": "5498e950-c9e9-43da-9b41-f215dbc9d2ef",
        "position": 13,
        "footystats_url": "https://footystats.org/clubs/fc-emmen-397",
        "primatips_url": "https:primatips.com/teams/netherlands/fc-emmen",
        "primatips_name": "Emmen",
        "league_name": "Eerste Divisie",
        "league_country": "Netherlands"
    },
    {
        "id": "eb4c37d4-71c4-4ee1-bb1a-cf94f1ef8c3b",
        "created_at": "2024-02-23T09:00:34.45046+00:00",
        "name": "FC Eindhoven",
        "league_id": "5498e950-c9e9-43da-9b41-f215dbc9d2ef",
        "position": 14,
        "footystats_url": "https://footystats.org/clubs/fc-eindhoven-394",
        "primatips_url": "https:primatips.com/teams/netherlands/fc-eindhoven",
        "primatips_name": "FC Eindhoven",
        "league_name": "Eerste Divisie",
        "league_country": "Netherlands"
    },
    {
        "id": "de6c35b5-214e-4f23-a8c2-6baa4ee1b96c",
        "created_at": "2024-02-23T09:00:34.45046+00:00",
        "name": "AFC Ajax II",
        "league_id": "5498e950-c9e9-43da-9b41-f215dbc9d2ef",
        "position": 15,
        "footystats_url": "https://footystats.org/clubs/afc-ajax-ii-400",
        "primatips_url": "https:primatips.com/teams/netherlands/jong-ajax",
        "primatips_name": "Jong Ajax",
        "league_name": "Eerste Divisie",
        "league_country": "Netherlands"
    },
    {
        "id": "bf781226-fdaa-40ec-b9a8-61dc7119516c",
        "created_at": "2024-02-23T09:00:34.45046+00:00",
        "name": "PSV Eindhoven II",
        "league_id": "5498e950-c9e9-43da-9b41-f215dbc9d2ef",
        "position": 16,
        "footystats_url": "https://footystats.org/clubs/psv-eindhoven-ii-392",
        "primatips_url": "https:primatips.com/teams/netherlands/fc-eindhoven",
        "primatips_name": "FC Eindhoven",
        "league_name": "Eerste Divisie",
        "league_country": "Netherlands"
    },
    {
        "id": "73d20817-2c0a-49fd-82b6-2ded6972b19a",
        "created_at": "2024-02-23T09:00:34.45046+00:00",
        "name": "FC Utrecht II",
        "league_id": "5498e950-c9e9-43da-9b41-f215dbc9d2ef",
        "position": 17,
        "footystats_url": "https://footystats.org/clubs/fc-utrecht-ii-399",
        "primatips_url": "https:primatips.com/teams/netherlands/jong-fc-utrecht",
        "primatips_name": "Jong Utrecht",
        "league_name": "Eerste Divisie",
        "league_country": "Netherlands"
    },
    {
        "id": "89cb327d-cc81-4abf-aa51-324e94d3a5d7",
        "created_at": "2024-02-23T09:00:34.45046+00:00",
        "name": "FC Den Bosch",
        "league_id": "5498e950-c9e9-43da-9b41-f215dbc9d2ef",
        "position": 18,
        "footystats_url": "https://footystats.org/clubs/fc-den-bosch-396",
        "primatips_url": "https:primatips.com/teams/netherlands/fc-den-bosch",
        "primatips_name": "Den Bosch",
        "league_name": "Eerste Divisie",
        "league_country": "Netherlands"
    },
    {
        "id": "9009f5e7-72e3-493f-9c15-ba5b5ef1b4e9",
        "created_at": "2024-02-23T09:00:34.45046+00:00",
        "name": "SC Telstar",
        "league_id": "5498e950-c9e9-43da-9b41-f215dbc9d2ef",
        "position": 19,
        "footystats_url": "https://footystats.org/clubs/sc-telstar-389",
        "primatips_url": "https:primatips.com/teams/netherlands/telstar-velsen",
        "primatips_name": "Telstar",
        "league_name": "Eerste Divisie",
        "league_country": "Netherlands"
    },
    {
        "id": "ff849d2c-19dc-4807-a4b8-3205dc891e75",
        "created_at": "2024-02-23T09:00:34.45046+00:00",
        "name": "FC Oss",
        "league_id": "5498e950-c9e9-43da-9b41-f215dbc9d2ef",
        "position": 20,
        "footystats_url": "https://footystats.org/clubs/fc-oss-391",
        "primatips_url": "https:primatips.com/teams/netherlands/top-oss",
        "primatips_name": "TOP Oss",
        "league_name": "Eerste Divisie",
        "league_country": "Netherlands"
    }
]